abf_explorer/__init__.py
abf_explorer/__main__.py
abf_explorer/abf.py
abf_explorer/abf_logging.py
abf_explorer/args.py
abf_explorer/filedisplay.py
abf_explorer/fileinfoplotcontrols.py
abf_explorer/gui.py
abf_explorer/plotting.py
abf_explorer/plotutils.py
abf_explorer-0.6.dist-info/LICENSE
abf_explorer-0.6.dist-info/METADATA
abf_explorer-0.6.dist-info/WHEEL
abf_explorer-0.6.dist-info/entry_points.txt
abf_explorer-0.6.dist-info/top_level.txt
abf_explorer-0.6.dist-info/RECORD
