Metadata-Version: 2.1
Name: abf-explorer
Version: 0.6
Summary: A PyQt GUI to quickly visualize ABF electrophysiology files
Home-page: https://github.com/nkicg6/ABF_Explorer
Author: Nick George
Author-email: nicholas.george32@gmail.com
License: GPL v3
Platform: UNKNOWN
Classifier: License :: OSI Approved :: GNU General Public License v3 or later (GPLv3+)
Classifier: Programming Language :: Python :: 3.7
Classifier: Natural Language :: English
Classifier: Intended Audience :: Science/Research
Classifier: Topic :: Scientific/Engineering :: Medical Science Apps.
Classifier: Topic :: Scientific/Engineering :: Visualization
Requires-Python: >=3.7
Requires-Dist: numpy (==1.19.4)
Requires-Dist: PyQt5 (==5.15.4)
Requires-Dist: pyqtgraph (==0.11.0)
Requires-Dist: pyabf (==2.2.8)
